[
    {
        "asset": {
            "ForeignAsset": "1"
        },
        "name": "Acala Dollar",
        "symbol": "AUSD",
        "decimals": 12,
        "currencyID": "1",
        "xcmInteriorKey": "[{\"network\":\"kusama\"},{\"parachain\":2000},{\"generalKey\":\"0x0081\"}]"
    },
    {
        "asset": {
            "ForeignAsset": "2"
        },
        "name": "Liquid KSM",
        "symbol": "LKSM",
        "decimals": 12,
        "currencyID": "2",
        "xcmInteriorKey": "[{\"network\":\"kusama\"},{\"parachain\":2000},{\"generalKey\":\"0x0083\"}]"
    },
    {
        "asset": {
            "ForeignAsset": "3"
        },
        "name": "Tether USD",
        "symbol": "USDT",
        "decimals": 6,
        "currencyID": "3",
        "xcmInteriorKey": "[{\"network\":\"kusama\"},{\"parachain\":1000},{\"palletInstance\":50},{\"generalIndex\":1984}]"
    },
    {
        "asset": {
            "ForeignAsset": "4"
        },
        "name": "Moonriver Token",
        "symbol": "MOVR",
        "decimals": 18,
        "currencyID": "4",
        "xcmInteriorKey": "[{\"network\":\"kusama\"},{\"parachain\":2023},{\"palletInstance\":10}]"
    },
    {
        "asset": {
            "ForeignAsset": "5"
        },
        "name": "Voucher KSM",
        "symbol": "VKSM",
        "decimals": 12,
        "currencyID": "5",
        "xcmInteriorKey": "[{\"network\":\"kusama\"},{\"parachain\":2001},{\"generalKey\":\"0x0104\"}]"
    },
    {
        "asset": {
            "Token": "DOT"
        },
        "name": "DOT",
        "symbol": "DOT",
        "decimals": 10
    },
    {
        "asset": {
            "Token": "IBTC"
        },
        "name": "IBTC",
        "symbol": "IBTC",
        "decimals": 8
    },
    {
        "asset": {
            "Token": "INTR"
        },
        "name": "INTR",
        "symbol": "INTR",
        "decimals": 10
    },
    {
        "asset": {
            "Token": "KBTC"
        },
        "name": "KBTC",
        "symbol": "KBTC",
        "decimals": 8,
        "xcmInteriorKey": "[{\"network\":\"kusama\"},{\"parachain\":2092},{\"generalKey\":\"0x000b\"}]"
    },
    {
        "asset": {
            "Token": "KINT"
        },
        "name": "KINT",
        "symbol": "KINT",
        "decimals": 12,
        "xcmInteriorKey": "[{\"network\":\"kusama\"},{\"parachain\":2092},{\"generalKey\":\"0x000c\"}]"
    },
    {
        "asset": {
            "Token": "KSM"
        },
        "name": "KSM",
        "symbol": "KSM",
        "decimals": 12
    }
]